{
  "inputs": {
    "demo/browser.js": {
      "bytes": 25186,
      "imports": [
        {
          "path": "dist/human.esm.js"
        },
        {
          "path": "demo/draw.js"
        },
        {
          "path": "demo/menu.js"
        },
        {
          "path": "demo/gl-bench.js"
        }
      ]
    },
    "demo/draw.js": {
      "bytes": 10436,
      "imports": []
    },
    "demo/gl-bench.js": {
      "bytes": 10782,
      "imports": []
    },
    "demo/menu.js": {
      "bytes": 13842,
      "imports": []
    },
    "dist/human.esm.js": {
      "bytes": 1783940,
      "imports": []
    }
  },
  "outputs": {
    "dist/demo-browser-index.js.map": {
      "imports": [],
      "inputs": {},
      "bytes": 2678157
    },
    "dist/demo-browser-index.js": {
      "imports": [],
      "exports": [],
      "inputs": {
        "dist/human.esm.js": {
          "bytesInOutput": 1776695
        },
        "demo/draw.js": {
          "bytesInOutput": 7668
        },
        "demo/menu.js": {
          "bytesInOutput": 11838
        },
        "demo/gl-bench.js": {
          "bytesInOutput": 7436
        },
        "demo/browser.js": {
          "bytesInOutput": 19407
        }
      },
      "bytes": 1830430
    }
  }
}
