{
  "inputs": {
    "demo/browser.js": {
      "bytes": 19806,
      "imports": [
        {
          "path": "dist/human.esm.js"
        },
        {
          "path": "demo/draw.js"
        },
        {
          "path": "demo/menu.js"
        }
      ]
    },
    "demo/draw.js": {
      "bytes": 9814,
      "imports": []
    },
    "demo/menu.js": {
      "bytes": 13845,
      "imports": []
    },
    "dist/human.esm.js": {
      "bytes": 2080824,
      "imports": []
    }
  },
  "outputs": {
    "dist/demo-browser-index.js.map": {
      "imports": [],
      "inputs": {},
      "bytes": 2844399
    },
    "dist/demo-browser-index.js": {
      "imports": [],
      "inputs": {
        "dist/human.esm.js": {
          "bytesInOutput": 1144406
        },
        "dist/human.esm.js": {
          "bytesInOutput": 319699
        },
        "dist/human.esm.js": {
          "bytesInOutput": 578472
        },
        "demo/draw.js": {
          "bytesInOutput": 9599
        },
        "demo/menu.js": {
          "bytesInOutput": 13821
        },
        "demo/browser.js": {
          "bytesInOutput": 17394
        }
      },
      "bytes": 2083513
    }
  }
}
